Metadata-Version: 2.1
Name: tpy112
Version: 0.0.1
Summary: A very basic calculator
Home-page: 
Author: Joshua Lowe
Author-email: josh@edublocks.org
License: MIT
Keywords: calculator
Classifier: Development Status :: 5 - Production/Stable
Classifier: Intended Audience :: Education
Classifier: Operating System :: Microsoft :: Windows :: Windows 10
Classifier: License :: OSI Approved :: MIT License
Classifier: Programming Language :: Python :: 3
License-File: LICENCE.txt
